.gitignore
.gitmodules
LICENSE
README.md
pyproject.toml
.github/workflows/deploy.yaml
simde_py/__init__.py
simde_py.egg-info/PKG-INFO
simde_py.egg-info/SOURCES.txt
simde_py.egg-info/dependency_links.txt
simde_py.egg-info/top_level.txt
simde_py/simde/amalgamate.py
simde_py/simde/simde/check.h
simde_py/simde/simde/debug-trap.h
simde_py/simde/simde/hedley.h
simde_py/simde/simde/simde-aes.h
simde_py/simde/simde/simde-align.h
simde_py/simde/simde/simde-arch.h
simde_py/simde/simde/simde-bf16.h
simde_py/simde/simde/simde-common.h
simde_py/simde/simde/simde-complex.h
simde_py/simde/simde/simde-constify.h
simde_py/simde/simde/simde-detect-clang.h
simde_py/simde/simde/simde-diagnostic.h
simde_py/simde/simde/simde-f16.h
simde_py/simde/simde/simde-features.h
simde_py/simde/simde/simde-math.h
simde_py/simde/simde/arm/neon.h
simde_py/simde/simde/arm/sve.h
simde_py/simde/simde/arm/neon/aba.h
simde_py/simde/simde/arm/neon/abal.h
simde_py/simde/simde/arm/neon/abal_high.h
simde_py/simde/simde/arm/neon/abd.h
simde_py/simde/simde/arm/neon/abdl.h
simde_py/simde/simde/arm/neon/abdl_high.h
simde_py/simde/simde/arm/neon/abs.h
simde_py/simde/simde/arm/neon/add.h
simde_py/simde/simde/arm/neon/addhn.h
simde_py/simde/simde/arm/neon/addhn_high.h
simde_py/simde/simde/arm/neon/addl.h
simde_py/simde/simde/arm/neon/addl_high.h
simde_py/simde/simde/arm/neon/addlv.h
simde_py/simde/simde/arm/neon/addv.h
simde_py/simde/simde/arm/neon/addw.h
simde_py/simde/simde/arm/neon/addw_high.h
simde_py/simde/simde/arm/neon/aes.h
simde_py/simde/simde/arm/neon/and.h
simde_py/simde/simde/arm/neon/bcax.h
simde_py/simde/simde/arm/neon/bic.h
simde_py/simde/simde/arm/neon/bsl.h
simde_py/simde/simde/arm/neon/cadd_rot270.h
simde_py/simde/simde/arm/neon/cadd_rot90.h
simde_py/simde/simde/arm/neon/cage.h
simde_py/simde/simde/arm/neon/cagt.h
simde_py/simde/simde/arm/neon/cale.h
simde_py/simde/simde/arm/neon/calt.h
simde_py/simde/simde/arm/neon/ceq.h
simde_py/simde/simde/arm/neon/ceqz.h
simde_py/simde/simde/arm/neon/cge.h
simde_py/simde/simde/arm/neon/cgez.h
simde_py/simde/simde/arm/neon/cgt.h
simde_py/simde/simde/arm/neon/cgtz.h
