Metadata-Version: 2.4
Name: simde-py
Version: 0.8.2.post1
Summary: SIMDe header build-requirements for Python C extensions
Author-email: miili <marius.isken@gmail.com>
License-Expression: MIT
Requires-Python: >=3.10
License-File: LICENSE
Dynamic: license-file
